AUTHORS.rst
CHANGES.rst
CONTRIBUTING.rst
LICENSE.txt
MANIFEST.in
README.rst
control_machine_requirements.txt
managed_node_requirements.txt
setup.cfg
setup.py
docs/Makefile
docs/make.bat
docs/build/doctrees/environment.pickle
docs/build/doctrees/index.doctree
docs/build/doctrees/installation.doctree
docs/build/html/.buildinfo
docs/build/html/genindex.html
docs/build/html/index.html
docs/build/html/installation.html
docs/build/html/objects.inv
docs/build/html/search.html
docs/build/html/searchindex.js
docs/build/html/_sources/index.txt
docs/build/html/_sources/installation.txt
docs/build/html/_static/ajax-loader.gif
docs/build/html/_static/basic.css
docs/build/html/_static/comment-bright.png
docs/build/html/_static/comment-close.png
docs/build/html/_static/comment.png
docs/build/html/_static/default.css
docs/build/html/_static/doctools.js
docs/build/html/_static/down-pressed.png
docs/build/html/_static/down.png
docs/build/html/_static/file.png
docs/build/html/_static/jquery.js
docs/build/html/_static/minus.png
docs/build/html/_static/plus.png
docs/build/html/_static/pygments.css
docs/build/html/_static/searchtools.js
docs/build/html/_static/sidebar.js
docs/build/html/_static/underscore.js
docs/build/html/_static/up-pressed.png
docs/build/html/_static/up.png
docs/build/html/_static/websupport.js
docs/build/html/_static/css/badge_only.css
docs/build/html/_static/css/theme.css
docs/build/html/_static/fonts/fontawesome-webfont.eot
docs/build/html/_static/fonts/fontawesome-webfont.svg
docs/build/html/_static/fonts/fontawesome-webfont.ttf
docs/build/html/_static/fonts/fontawesome-webfont.woff
docs/build/html/_static/js/theme.js
docs/source/authors.rst
docs/source/changes.rst
docs/source/conf.py
docs/source/contributing.rst
docs/source/index.rst
docs/source/installation.rst
docs/source/user_guide.rst
supervisorclusterctl/__init__.py
supervisorclusterctl/supervisorclusterctl.py
supervisorclusterctl.egg-info/PKG-INFO
supervisorclusterctl.egg-info/SOURCES.txt
supervisorclusterctl.egg-info/dependency_links.txt
supervisorclusterctl.egg-info/entry_points.txt
supervisorclusterctl.egg-info/top_level.txt
test/test_supervisorclusterctl.py