Metadata-Version: 1.0
Name: supervisorclusterctl
Version: 0.1.2
Summary: supervisorclusterctl is a cmd line tool that allows to control a cluster of processes by utilizing Supervisor and Ansible.
Home-page: https://github.com/RobWin/supervisorclusterctl.git
Author: Robert Winkler
Author-email: rbrtwnklr@gmail.com
License: GPLv3
Keywords: supervisor ansible
Platform: UNKNOWN
